easy_icons/__init__.py
easy_icons/apps.py
easy_icons/base.py
easy_icons/exceptions.py
easy_icons/renderers.py
easy_icons/templatetags/__init__.py
easy_icons/templatetags/easy_icons.py
easy_icons/utils.py
django_easy_icons-1.1.1.dist-info/LICENSE
django_easy_icons-1.1.1.dist-info/METADATA
django_easy_icons-1.1.1.dist-info/WHEEL
django_easy_icons-1.1.1.dist-info/RECORD
