Metadata-Version: 2.1
Name: django-easy-icons
Version: 1.1.1
Summary: Easy, flexible icons for Django
Home-page: https://github.com/SamuelJennings/django-easy-icons
License: MIT
Author: Sam
Author-email: samuel.scott.jennings@gmail.com
Requires-Python: >=3.10,<4.0
Classifier: License :: OSI Approved :: MIT License
Classifier: Programming Language :: Python :: 3
Classifier: Programming Language :: Python :: 3.10
Classifier: Programming Language :: Python :: 3.11
Classifier: Programming Language :: Python :: 3.12
Requires-Dist: django
